LICENSE
MANIFEST.in
README.md
install_script.py
setup.py
kdDesktopAssistant/__init__.py
kdDesktopAssistant/app_data.py
kdDesktopAssistant/dl_launch_item_detail.py
kdDesktopAssistant/dl_launch_item_detail.ui
kdDesktopAssistant/fileutil.py
kdDesktopAssistant/item_popup_menu.py
kdDesktopAssistant/kdDesktopAssistant.py
kdDesktopAssistant/kdDesktopAssistant.ui
kdDesktopAssistant/kdconfig.py
kdDesktopAssistant/launch_item.py
kdDesktopAssistant/session.py
kdDesktopAssistant/session.ui
kdDesktopAssistant.egg-info/PKG-INFO
kdDesktopAssistant.egg-info/SOURCES.txt
kdDesktopAssistant.egg-info/dependency_links.txt
kdDesktopAssistant.egg-info/entry_points.txt
kdDesktopAssistant.egg-info/not-zip-safe
kdDesktopAssistant.egg-info/requires.txt
kdDesktopAssistant.egg-info/top_level.txt
kdDesktopAssistant/data/profile.ini
kdDesktopAssistant/data/db/kdDesktopAssistant.db
kdDesktopAssistant/data/image/S60922-232113.jpg
kdDesktopAssistant/data/image/S60922-232638.jpg
kdDesktopAssistant/data/image/bg_catelog.jpg
kdDesktopAssistant/data/image/catelog.svg
kdDesktopAssistant/data/image/default128.png
kdDesktopAssistant/data/image/default48.png
kdDesktopAssistant/data/image/file.png
kdDesktopAssistant/data/image/firefox64.png
kdDesktopAssistant/data/image/folder.svg
kdDesktopAssistant/data/image/gnome.png
kdDesktopAssistant/data/image/logo.png